{"frames":{"forms/ellipse":{"frame":{"x":2,"y":2,"w":900,"h":900},"rotated":false,"trimmed":false,"spriteSourceSize":{"x":0,"y":0,"w":900,"h":900},"sourceSize":{"w":900,"h":900},"pivot":{"x":0,"y":0}},"forms/rectangle":{"frame":{"x":2,"y":906,"w":900,"h":900},"rotated":false,"trimmed":false,"spriteSourceSize":{"x":0,"y":0,"w":900,"h":900},"sourceSize":{"w":900,"h":900},"pivot":{"x":0,"y":0}},"forms/rhombus":{"frame":{"x":2,"y":1810,"w":900,"h":900},"rotated":false,"trimmed":false,"spriteSourceSize":{"x":0,"y":0,"w":900,"h":900},"sourceSize":{"w":900,"h":900},"pivot":{"x":0,"y":0}},"forms/triangle":{"frame":{"x":2,"y":2714,"w":900,"h":900},"rotated":false,"trimmed":false,"spriteSourceSize":{"x":0,"y":0,"w":900,"h":900},"sourceSize":{"w":900,"h":900},"pivot":{"x":0,"y":0}}},"meta":{"app":"http://github.com/odrick/free-tex-packer-core","version":"0.3.4","image":"assets.png","format":"RGBA8888","size":{"w":904,"h":3616},"scale":1}}